{"zingmp3.vn":{"/":{"zmp3_app_version.1":{"key":"zmp3_app_version.1","value":"1025","expires":"2022-03-09T04:31:39.000Z","maxAge":31536000,"domain":"zingmp3.vn","path":"/","hostOnly":false,"creation":"2021-03-09T03:20:22.732Z","lastAccessed":"2021-04-16T09:40:21.158Z"},"zmp3_rqid":{"key":"zmp3_rqid","value":"MHw0Mi4xMTkdUngMjYdUngMjMyfDEwMjV8MTYxODU2NjAyMTU3OA","expires":"2021-06-20T09:40:21.000Z","maxAge":5616000,"domain":"zingmp3.vn","path":"/","hostOnly":false,"creation":"2021-03-09T03:20:22.734Z","lastAccessed":"2021-04-16T09:40:21.237Z"},"zmp3_rqid_lagecy":{"key":"zmp3_rqid_lagecy","value":"MHw0Mi4xMTgdUngMTmUsIC1LjI0MnxdUngdWxsfDE2MTU4NjkxMjQ2Njk","expires":"2021-05-20T04:32:04.000Z","maxAge":5616000,"domain":"zingmp3.vn","path":"/","secure":true,"httpOnly":true,"hostOnly":false,"creation":"2021-03-09T04:23:43.169Z","lastAccessed":"2021-04-16T09:40:21.158Z"}}}}